{"cameraMode":{"drawMode":0,"name":"Shaded","section":"Shading Mode"},"sceneLighting":true,"audioPlay":false,"sceneViewState":{"showFog":true,"showMaterialUpdate":false,"showSkybox":true,"showFlares":true,"showImageEffects":true,"showParticleSystems":true},"in2DMode":false,"pivot":{"x":-1.3574506044387818,"y":2.6671812534332277,"z":3.124868154525757},"rotation":{"x":0.04077402502298355,"y":-0.026966748759150506,"z":0.0015145379584282637,"w":0.9988759756088257},"size":2.0849032402038576,"orthographic":false}